Metadata-Version: 2.1
Name: mwsqlite
Version: 1.2.2
Summary: Simply python library for interact with (EOSIO) WAX blockchain
Home-page: https://github.com/makarworld/mwsqlite.git
Download-URL: https://github.com/makarworld/mwsqlite/archive/refs/tags/v1.2.2.zip
Author: abuztrade
Author-email: abuztrade.work@gmail.com
License: MIT License
Classifier: Development Status :: 4 - Beta
Classifier: Topic :: Communications :: Email
Classifier: Operating System :: OS Independent
Classifier: License :: OSI Approved :: MIT License
Classifier: Programming Language :: Python :: 3
Classifier: Programming Language :: Python :: 3.6
Classifier: Programming Language :: Python :: 3.7
Classifier: Programming Language :: Python :: 3.8
Classifier: Programming Language :: Python :: 3.9
Classifier: Programming Language :: Python :: 3.10
Classifier: Intended Audience :: Developers
Classifier: Intended Audience :: Customer Service
Classifier: Intended Audience :: Financial and Insurance Industry
Requires-Python: >=3.6.0
License-File: LICENSE
